{
  "assets_bucket_name": {
    "sensitive": false,
    "type": "string",
    "value": "bedrock-assets-alt-soe-025-4831"
  },
  "cluster_endpoint": {
    "sensitive": false,
    "type": "string",
    "value": "https://B6FA4A7C915FC02264BE4E496B3D0999.gr7.us-east-1.eks.amazonaws.com"
  },
  "cluster_name": {
    "sensitive": false,
    "type": "string",
    "value": "project-bedrock-cluster"
  },
  "dynamodb_table_name": {
    "sensitive": false,
    "type": "string",
    "value": "project-bedrock-carts"
  },
  "mysql_endpoint": {
    "sensitive": false,
    "type": "string",
    "value": "project-bedrock-mysql.c49wwquaihhd.us-east-1.rds.amazonaws.com:3306"
  },
  "postgres_endpoint": {
    "sensitive": false,
    "type": "string",
    "value": "project-bedrock-postgres.c49wwquaihhd.us-east-1.rds.amazonaws.com:5432"
  },
  "region": {
    "sensitive": false,
    "type": "string",
    "value": "us-east-1"
  },
  "vpc_id": {
    "sensitive": false,
    "type": "string",
    "value": "vpc-06b857299e07a5706"
  }
}
